anixart/__init__.py
anixart/__meta__.py
anixart/api.py
anixart/auth/__init__.py
anixart/auth/account.py
anixart/auth/error_handler.py
anixart/auth/objects.py
anixart/endpoints.py
anixart/enums.py
anixart/exceptions.py
anixart/profile/__init__.py
anixart/profile/error_handler.py
anixart/profile/objects.py
anixart-0.3.0.1.dist-info/LICENSE
anixart-0.3.0.1.dist-info/METADATA
anixart-0.3.0.1.dist-info/WHEEL
anixart-0.3.0.1.dist-info/RECORD
