Metadata-Version: 2.3
Name: anixart
Version: 0.3.0.1
Summary: Wrapper for using the Anixart API.
License: FPA License
Author: SantaSpeen
Author-email: santaspeen@gmail.com
Requires-Python: >=3.10,<4.0
Classifier: Development Status :: 2 - Pre-Alpha
Classifier: License :: Other/Proprietary License
Classifier: Programming Language :: Python :: 3
Classifier: Programming Language :: Python :: 3.10
Classifier: Programming Language :: Python :: 3.11
Classifier: Programming Language :: Python :: 3.12
Classifier: Programming Language :: Python :: 3.13
Classifier: Topic :: Software Development :: Libraries :: Python Modules
Requires-Dist: requests (>=2.32.3,<3.0.0)
Project-URL: Repository, https://github.com/SantaSpeen/anixart
